agent_framework/__init__.py
agent_framework/py.typed
agent_framework/chart_generation/llm_refinement_loop.py
agent_framework/core/__init__.py
agent_framework/core/activity_formatter.py
agent_framework/core/agent_interface.py
agent_framework/core/agent_provider.py
agent_framework/core/base_agent.py
agent_framework/core/elasticsearch_config_provider.py
agent_framework/core/implementation_validator.py
agent_framework/core/model_clients.py
agent_framework/core/model_config.py
agent_framework/core/model_router.py
agent_framework/core/models.py
agent_framework/core/rich_content_prompt_unsused_to_be_deleted.py
agent_framework/core/state_manager.py
agent_framework/core/step_display_config.py
agent_framework/core/streaming_parts_accumulator.py
agent_framework/implementations/__init__.py
agent_framework/implementations/llamaindex_agent.py
agent_framework/implementations/llamaindex_memory_adapter.py
agent_framework/implementations/microsoft_agent.py
agent_framework/memory/__init__.py
agent_framework/memory/agent_mixin.py
agent_framework/memory/base.py
agent_framework/memory/config.py
agent_framework/memory/manager.py
agent_framework/memory/tools.py
agent_framework/memory/providers/__init__.py
agent_framework/memory/providers/graphiti_provider.py
agent_framework/memory/providers/memori_provider.py
agent_framework/monitoring/__init__.py
agent_framework/monitoring/api_timing_tracker.py
agent_framework/monitoring/elasticsearch_circuit_breaker.py
agent_framework/monitoring/elasticsearch_logging.py
agent_framework/monitoring/error_handling.py
agent_framework/monitoring/error_logging.py
agent_framework/monitoring/llm_metrics.py
agent_framework/monitoring/llm_metrics_collector.py
agent_framework/monitoring/llm_metrics_logger.py
agent_framework/monitoring/metrics_config.py
agent_framework/monitoring/observability_manager.py
agent_framework/monitoring/otel_instrumentor.py
agent_framework/monitoring/otel_logging_handler.py
agent_framework/monitoring/otel_metrics_recorder.py
agent_framework_lib-0.5.8.post21.dist-info/licenses/LICENSE
agent_framework_lib-0.5.8.post21.dist-info/METADATA
agent_framework_lib-0.5.8.post21.dist-info/WHEEL
agent_framework_lib-0.5.8.post21.dist-info/entry_points.txt
agent_framework_lib-0.5.8.post21.dist-info/top_level.txt
agent_framework_lib-0.5.8.post21.dist-info/RECORD
