Metadata-Version: 2.4
Name: agent-framework-lib
Version: 0.5.8.post21
Summary: A comprehensive Python framework for building and serving conversational AI agents with FastAPI
Author-email: Sebastian Pavel <sebastian@cinco.ai>, Elliott Girard <elliott.girard@icloud.com>
Maintainer-email: Sebastian Pavel <sebastian@cinco.ai>
License: MIT
Project-URL: Homepage, https://github.com/Cinco-AI/AgentFramework
Project-URL: Repository, https://github.com/Cinco-AI/AgentFramework.git
Project-URL: Issues, https://github.com/Cinco-AI/AgentFramework/issues
Project-URL: Documentation, https://github.com/Cinco-AI/AgentFramework/blob/main/README.md
Project-URL: Changelog, https://github.com/Cinco-AI/AgentFramework/blob/main/docs/CHANGELOG.md
Project-URL: Bug Tracker, https://github.com/Cinco-AI/AgentFramework/issues
Project-URL: Source Code, https://github.com/Cinco-AI/AgentFramework
Keywords: ai,agents,fastapi,llamaindex,framework,conversational-ai,multi-agent,llm,openai,gemini,chatbot,session-management,framework-agnostic
Classifier: Development Status :: 4 - Beta
Classifier: Intended Audience :: Developers
Classifier: License :: OSI Approved :: MIT License
Classifier: Operating System :: OS Independent
Classifier: Programming Language :: Python :: 3
Classifier: Programming Language :: Python :: 3.10
Classifier: Programming Language :: Python :: 3.11
Classifier: Programming Language :: Python :: 3.12
Classifier: Programming Language :: Python :: 3.13
Classifier: Programming Language :: Python :: 3 :: Only
Classifier: Topic :: Software Development :: Libraries :: Python Modules
Classifier: Topic :: Scientific/Engineering :: Artificial Intelligence
Classifier: Topic :: Communications :: Chat
Classifier: Topic :: Internet :: WWW/HTTP :: HTTP Servers
Classifier: Framework :: FastAPI
Classifier: Environment :: Web Environment
Classifier: Typing :: Typed
Requires-Python: <3.14,>=3.10
License-File: LICENSE
Requires-Dist: aiofiles>=24.1.0
Requires-Dist: fastapi>=0.115.12
Requires-Dist: uvicorn>=0.34.2
Requires-Dist: fastmcp>=2.2.7
Requires-Dist: mcp-python-interpreter
Requires-Dist: pyyaml>=6.0.2
Requires-Dist: pydantic>=2.0.0
Requires-Dist: opentelemetry-sdk>=1.33.1
Requires-Dist: opentelemetry-api>=1.33.1
Requires-Dist: opentelemetry-exporter-otlp-proto-grpc>=1.33.1
Requires-Dist: pymongo>=4.10.1
Requires-Dist: motor>=3.6.0
Requires-Dist: black>=25.1.0
Requires-Dist: markitdown[all]>=0.1.2
Requires-Dist: psutil>=7.0.0
Requires-Dist: weasyprint>=60.0
Requires-Dist: markdown>=3.5
Requires-Dist: playwright>=1.56.0
Requires-Dist: elasticsearch<9.0.0,>=8.11.0
Requires-Dist: ddgs>=9.9.3
Requires-Dist: llama-index>=0.14.10
Requires-Dist: llama-index-core>=0.12.0
Requires-Dist: llama-index-llms-openai>=0.4.0
Requires-Dist: llama-index-llms-anthropic>=0.9.5
Requires-Dist: llama-index-llms-google-genai>=0.1.0
Requires-Dist: graphiti-core>=0.24.3
Requires-Dist: tiktoken>=0.7.0
Requires-Dist: falkordb>=1.0.0
Provides-Extra: llamaindex
Requires-Dist: llama-index-core>=0.12.0; extra == "llamaindex"
Requires-Dist: llama-index>=0.12.0; extra == "llamaindex"
Requires-Dist: llama-index-llms-openai>=0.4.0; extra == "llamaindex"
Requires-Dist: llama-index-llms-google-genai>=0.1.0; extra == "llamaindex"
Requires-Dist: llama-index-llms-anthropic>=0.9.5; extra == "llamaindex"
Provides-Extra: mcp
Requires-Dist: llama-index-tools-mcp>=0.4.0; extra == "mcp"
Provides-Extra: websearch
Requires-Dist: ddgs>=8.0.0; extra == "websearch"
Provides-Extra: microsoft
Provides-Extra: dev
Requires-Dist: pytest>=8.4.0; extra == "dev"
Requires-Dist: pytest-asyncio>=0.21.0; extra == "dev"
Requires-Dist: pytest-cov>=6.2.1; extra == "dev"
Requires-Dist: pytest-mock>=3.10.0; extra == "dev"
Requires-Dist: pytest-benchmark>=4.0.0; extra == "dev"
Requires-Dist: pytest-xdist>=3.3.0; extra == "dev"
Requires-Dist: black>=25.1.0; extra == "dev"
Requires-Dist: flake8>=6.0.0; extra == "dev"
Requires-Dist: mypy>=1.5.0; extra == "dev"
Requires-Dist: ruff>=0.1.0; extra == "dev"
Requires-Dist: pre-commit>=3.0.0; extra == "dev"
Requires-Dist: aiohttp>=3.12.13; extra == "dev"
Requires-Dist: httpx>=0.28.1; extra == "dev"
Requires-Dist: coverage>=7.0.0; extra == "dev"
Provides-Extra: mongodb
Requires-Dist: pymongo>=4.10.1; extra == "mongodb"
Requires-Dist: motor>=3.6.0; extra == "mongodb"
Provides-Extra: elasticsearch
Requires-Dist: elasticsearch>=8.11.0; extra == "elasticsearch"
Provides-Extra: s3
Requires-Dist: boto3>=1.34.0; extra == "s3"
Requires-Dist: botocore>=1.34.0; extra == "s3"
Provides-Extra: minio
Requires-Dist: minio>=7.2.0; extra == "minio"
Provides-Extra: gcp
Requires-Dist: google-cloud-storage>=2.14.0; extra == "gcp"
Provides-Extra: multimodal
Requires-Dist: pillow>=10.0.0; extra == "multimodal"
Requires-Dist: opencv-python>=4.8.0; extra == "multimodal"
Requires-Dist: pytesseract>=0.3.10; extra == "multimodal"
Provides-Extra: memory
Requires-Dist: memori>=0.1.0; extra == "memory"
Requires-Dist: graphiti-core>=0.3.0; extra == "memory"
Provides-Extra: memori
Requires-Dist: memori>=0.1.0; extra == "memori"
Provides-Extra: graphiti
Requires-Dist: graphiti-core>=0.24.3; extra == "graphiti"
Provides-Extra: graphiti-falkordb
Requires-Dist: graphiti-core[falkordb]>=0.24.3; extra == "graphiti-falkordb"
Provides-Extra: graphiti-neo4j
Requires-Dist: graphiti-core>=0.24.3; extra == "graphiti-neo4j"
Requires-Dist: neo4j>=5.0.0; extra == "graphiti-neo4j"
Provides-Extra: graphiti-all
Requires-Dist: graphiti-core[falkordb]>=0.24.3; extra == "graphiti-all"
Requires-Dist: neo4j>=5.0.0; extra == "graphiti-all"
Provides-Extra: all
Requires-Dist: agent-framework-lib[dev,elasticsearch,gcp,graphiti-all,llamaindex,mcp,memory,microsoft,minio,mongodb,multimodal,s3,websearch]; extra == "all"
Dynamic: license-file
